purgeraw/__init__.py
purgeraw/deletion.py
purgeraw/directory_walker.py
purgeraw/index_extraction.py
purgeraw/main.py
purgeraw/purger.py
purgeraw-1.0.5.dist-info/entry_points.txt
purgeraw-1.0.5.dist-info/LICENSE
purgeraw-1.0.5.dist-info/WHEEL
purgeraw-1.0.5.dist-info/METADATA
purgeraw-1.0.5.dist-info/RECORD
