Metadata-Version: 2.1
Name: purgeraw
Version: 1.0.5
Summary: Utility to remove unprocessed RAW files from a folder keeping only RAW files that yielded results
Home-page: https://github.com/andyphelps/purgeraw
License: MIT
Author: Andy Phelps
Author-email: andrew.m.phelps@gmail.com
Requires-Python: >=3.8,<4.0
Classifier: License :: OSI Approved :: MIT License
Classifier: Programming Language :: Python :: 3
Classifier: Programming Language :: Python :: 3.8
Requires-Dist: click (>=7.1.2,<8.0.0)
Requires-Dist: toolz (>=0.10.0,<0.11.0)
Project-URL: Repository, https://github.com/andyphelps/purgeraw
